watchdict/__init__.py
watchdict-0.1.3.dist-info/METADATA
watchdict-0.1.3.dist-info/WHEEL
watchdict-0.1.3.dist-info/top_level.txt
watchdict-0.1.3.dist-info/RECORD
