Metadata-Version: 2.1
Name: watchdict
Version: 0.1.3
Summary: A dictionary class with change detection and state persistence
Home-page: https://github.com/yourusername/watchdict
Author: Chocolate
Author-email: theerilia@gmail.com
License: MIT
Classifier: Programming Language :: Python :: 3
Classifier: License :: OSI Approved :: MIT License
Classifier: Operating System :: OS Independent
Requires-Python: >=3.6
